odoo/addons/l10n_th_sequence_preview/README.rst
odoo/addons/l10n_th_sequence_preview/__init__.py
odoo/addons/l10n_th_sequence_preview/__manifest__.py
odoo/addons/l10n_th_sequence_preview/i18n/l10n_th_sequence_preview.pot
odoo/addons/l10n_th_sequence_preview/models/__init__.py
odoo/addons/l10n_th_sequence_preview/models/ir_sequence.py
odoo/addons/l10n_th_sequence_preview/models/ir_sequence_date_range.py
odoo/addons/l10n_th_sequence_preview/readme/CONTRIBUTORS.rst
odoo/addons/l10n_th_sequence_preview/readme/DESCRIPTION.rst
odoo/addons/l10n_th_sequence_preview/readme/HISTORY.rst
odoo/addons/l10n_th_sequence_preview/static/description/icon.png
odoo/addons/l10n_th_sequence_preview/static/description/index.html
odoo/addons/l10n_th_sequence_preview/tests/__init__.py
odoo/addons/l10n_th_sequence_preview/tests/test_ir_sequence_date_range_preview.py
odoo/addons/l10n_th_sequence_preview/tests/test_ir_sequence_preview.py
odoo/addons/l10n_th_sequence_preview/views/ir_sequence_view.xml
odoo14_addon_l10n_th_sequence_preview-14.0.1.0.1.dev5.dist-info/METADATA
odoo14_addon_l10n_th_sequence_preview-14.0.1.0.1.dev5.dist-info/WHEEL
odoo14_addon_l10n_th_sequence_preview-14.0.1.0.1.dev5.dist-info/top_level.txt
odoo14_addon_l10n_th_sequence_preview-14.0.1.0.1.dev5.dist-info/RECORD
